tractor_db/__init__.py
tractor_db/db.json
tractor_db/main.py
tractor_db-0.2.0.dist-info/METADATA
tractor_db-0.2.0.dist-info/WHEEL
tractor_db-0.2.0.dist-info/entry_points.txt
tractor_db-0.2.0.dist-info/top_level.txt
tractor_db-0.2.0.dist-info/RECORD
