Metadata-Version: 2.1
Name: tractor_db
Version: 0.2.0
Summary: A package to get random tractor information
Author: Mike Lawson
Author-email: mike@allmachines.com
Project-URL: Homepage, https://www.allmachines.com/tractors
Classifier: Programming Language :: Python :: 3
Classifier: License :: OSI Approved :: MIT License
Classifier: Operating System :: OS Independent
Requires-Python: >=3.6
